yandex_quasar_cli/__init__.py
yandex_quasar_cli/__main__.py
yandex_quasar_cli/actions.py
yandex_quasar_cli/cli.py
yandex_quasar_cli/settings.py
yandex_quasar_cli/quasar_types/__init__.py
yandex_quasar_cli/quasar_types/quasar_capabilities.py
yandex_quasar_cli/quasar_types/quasar_capability_on_off.py
yandex_quasar_cli/quasar_types/quasar_device_action.py
yandex_quasar_cli/quasar_types/quasar_primary.py
yandex_quasar_cli/quasar_types/quasar_properties.py
yandex_quasar_cli-0.1.3.dist-info/LICENSE
yandex_quasar_cli-0.1.3.dist-info/METADATA
yandex_quasar_cli-0.1.3.dist-info/WHEEL
yandex_quasar_cli-0.1.3.dist-info/entry_points.txt
yandex_quasar_cli-0.1.3.dist-info/top_level.txt
yandex_quasar_cli-0.1.3.dist-info/RECORD
