Metadata-Version: 2.1
Name: yandex-quasar-cli
Version: 0.1.3
Summary: Command line interface for Yandex Smart Home API
Home-page: https://github.com/p1ne/yandex-quasar-cli
Author: p1ne
Author-email: 
License: Apache-2.0
Project-URL: Homepage, https://github.com/p1ne/yandex-quasar-cli
Project-URL: Changelog, https://github.com/p1ne/yandex-quasar-cli/releases
Project-URL: Issues, https://github.com/p1ne/yandex-quasar-cli/issues
Project-URL: CI, https://github.com/p1ne/yandex-quasar-cli/actions
Keywords: yandex,quasar,smart home,cli
Classifier: License :: OSI Approved :: Apache Software License
Requires-Python: >=3.10
License-File: LICENSE
Requires-Dist: click >=8.1.7
Requires-Dist: msgspec >=0.18.6
Requires-Dist: pprintpp >=0.4.0
Requires-Dist: flatdict >=4.0.1
Requires-Dist: anyconfig >=0.14.0
Requires-Dist: deepdiff >=6.7.1
Requires-Dist: twine >=5.0.0
Requires-Dist: build >=1.1.1
Provides-Extra: test
Requires-Dist: pytest ; extra == 'test'
